README.rst
setup.py
django_sifac.egg-info/PKG-INFO
django_sifac.egg-info/SOURCES.txt
django_sifac.egg-info/dependency_links.txt
django_sifac.egg-info/requires.txt
django_sifac.egg-info/top_level.txt
sifac/__init__.py
sifac/admin.py
sifac/forms.py
sifac/models.py
sifac/service.py
sifac/tests.py
sifac/utils.py
sifac/locale/fr/LC_MESSAGES/django.po
sifac/sap/__init__.py
sifac/sap/db.py
sifac/sap/models.py
tests/test_db.py
tests/test_model_cost_center.py
tests/test_model_eotp.py
tests/test_model_functional_domain.py
tests/test_model_fund.py
tests/test_model_sifac.py