Metadata-Version: 1.0
Name: django-sifac
Version: 0.3.0
Summary: A SAP API for SIFAC
Home-page: https://github.com/unistra/django-sifac/
Author: Arnaud Grausem
Author-email: arnaud.grausem@unistra.fr
License: CeCILL-B
Keywords: sifac sap django
Platform: UNKNOWN
